{
"DefaultValues": {

"interstitials_enabled":true,
"interstitials_frequency": 60,
// BOOSTERS
"round_boosters_frequency": 40,
"profit_round_booster_duration": 120,
"speed_round_booster_duration": 120,

"droneX10RewardEnable": true,

// BALANCE
"upgradePriceTicket": 1 ,
"upgradePriceSpeed": 1,
"upgradePriceSlide": 1,
"xpToLevelUpFactor": 1,
"duckPayoutProfit": 1.2,
"levelUpTimeBase":true,

"tutorial":true,
"ornament_for_video": false,
"skins_system":true,
"world2_unlock_timer_enable":false,
"world2_unlock_hours":24,
"world2_unlock_at_level":20,
"world3_unlock_at_level":40,
"zoom_out":true,
"slower_gameplay":false,
"show_upper_buttons":true,
"content_burn":true,
"ab_test_new_users": 100
},

"ABTests": [
  {
"id": "A",
"CohortWeight": 1,
"values": {
"content_burn":true
}
},

{
"id": "B",
"CohortWeight": 97,
"values": {
"interstitials_enabled":true,
"content_burn":true
}
},
  
{
"id": "C",
"CohortWeight": 1,
"values": {
"interstitials_enabled":true
}
},
  
{
"id": "D",
"CohortWeight": 1,
"values": {
"interstitials_enabled":false
}
}
]
}
